carbonara_idb/__init__.py
carbonara_idb/analysis.py
carbonara_idb/fileformat.py
carbonara_idb/idapython.py
carbonara_idb/netnode.py
carbonara_idb-0.4.0.post3.dist-info/DESCRIPTION.rst
carbonara_idb-0.4.0.post3.dist-info/METADATA
carbonara_idb-0.4.0.post3.dist-info/RECORD
carbonara_idb-0.4.0.post3.dist-info/WHEEL
carbonara_idb-0.4.0.post3.dist-info/entry_points.txt
carbonara_idb-0.4.0.post3.dist-info/metadata.json
carbonara_idb-0.4.0.post3.dist-info/top_level.txt
