Metadata-Version: 2.0
Name: carbonara-idb
Version: 0.4.0-3
Summary: Pure Python parser for IDA Pro databases (.idb files). Fork used in Guanciale.
Home-page: https://github.com/Carbonara-Project/Carbonara-IDB
Author: Andrea Fioraldi
Author-email: andreafioraldi@gmail.com
License: Apache License 2.0
Platform: UNKNOWN
Classifier: License :: OSI Approved :: Apache Software License
Classifier: Programming Language :: Python :: 2.7
Requires-Dist: six
Requires-Dist: hexdump
Requires-Dist: vivisect-vstruct-wb (>=1.0.3)
